controller.v
module controller (
    input wire clk, reset,
    output reg [6:0] A, B,
    output reg OP
);
    reg [2:0] pstate, nstate;
    
    parameter [2:0] START = 3'b000,
                    TEST_NOT = 3'b001,
                    TEST_SHR = 3'b010,
                    FINISH = 3'b011;
    
    // State register
    always @(posedge clk or posedge reset) begin
        if (reset)
            pstate <= START;
        else
            pstate <= nstate;
    end
    
    // Next state and output logic
    always @(*) begin
        // Default outputs
        A = 7'b0000000;
        B = 7'b0000000;
        OP = 1'b0;
        nstate = pstate;
        
        case (pstate)
            START: begin
                nstate = TEST_NOT;
            end
            
            TEST_NOT: begin
                A = 7'b1010101;  // Test pattern for NOT
                B = 7'b0000000;  // Not used for NOT operation
                OP = 1'b0;       // NOT operation
                nstate = TEST_SHR;
            end
            
            TEST_SHR: begin
                A = 7'b1100110;  // Test pattern for SHR
                B = 7'b0000011;  // Shift by 3
                OP = 1'b1;      // SHR operation
                nstate = FINISH;
            end
            
            FINISH: begin
                nstate = START;
            end
            
            default: nstate = START;
        endcase
    end
endmodule

controller_tb.v
`timescale 1ns/1ns
module controller_tb;

    reg clk, reset;
    wire [6:0] A, B;
    wire OP;
    
    controller uut (
        .clk(clk),
        .reset(reset),
        .A(A),
        .B(B),
        .OP(OP)
    );
    
    initial begin
        clk = 0;
        forever #5 clk = ~clk;
    end
    
    initial begin
        $dumpfile("controller_test.vcd");
        $dumpvars(0, controller_tb);
        
        reset = 1;
        #10;
        reset = 0;
        
        #100;
        $finish;
    end
    
    initial begin
        $monitor("Time=%3t State=%b A=%b B=%b OP=%b", 
                $time, uut.pstate, A, B, OP);
    end
endmodule

controller_test.vcd
$date
	Sun Jun  8 23:02:36 2025
$end
$version
	Icarus Verilog
$end
$timescale
	1ns
$end
$scope module controller_tb $end
$var wire 1 ! OP $end
$var wire 7 " B [6:0] $end
$var wire 7 # A [6:0] $end
$var reg 1 $ clk $end
$var reg 1 % reset $end
$scope module uut $end
$var wire 1 $ clk $end
$var wire 1 % reset $end
$var parameter 3 & FINISH $end
$var parameter 3 ' START $end
$var parameter 3 ( TEST_NOT $end
$var parameter 3 ) TEST_SHR $end
$var reg 7 * A [6:0] $end
$var reg 7 + B [6:0] $end
$var reg 1 ! OP $end
$var reg 3 , nstate [2:0] $end
$var reg 3 - pstate [2:0] $end
$upscope $end
$upscope $end
$enddefinitions $end
$comment Show the parameter values. $end
$dumpall
b10 )
b1 (
b0 '
b11 &
$end
#0
$dumpvars
b0 -
b1 ,
b0 +
b0 *
1%
0$
b0 #
b0 "
0!
$end
#5
1$
#10
0$
0%
#15
b10 ,
b1010101 #
b1010101 *
b1 -
1$
#20
0$
#25
b11 ,
1!
b11 "
b11 +
b1100110 #
b1100110 *
b10 -
1$
#30
0$
#35
b0 ,
0!
b0 "
b0 +
b0 #
b0 *
b11 -
1$
#40
0$
#45
b1 ,
b0 -
1$
#50
0$
#55
b10 ,
b1010101 #
b1010101 *
b1 -
1$
#60
0$
#65
b11 ,
1!
b11 "
b11 +
b1100110 #
b1100110 *
b10 -
1$
#70
0$
#75
b0 ,
0!
b0 "
b0 +
b0 #
b0 *
b11 -
1$
#80
0$
#85
b1 ,
b0 -
1$
#90
0$
#95
b10 ,
b1010101 #
b1010101 *
b1 -
1$
#100
0$
#105
b11 ,
1!
b11 "
b11 +
b1100110 #
b1100110 *
b10 -
1$
