ALU_SHR_7bit.v
module ALU_SHR_7bit (
    input wire [6:0] in,
    input wire [2:0] shift,  // Shift amount (0-7)
    output reg [6:0] out
);
    always @(*) begin
        case(shift)
            3'b000: out = in;
            3'b001: out = {1'b0, in[6:1]};
            3'b010: out = {2'b00, in[6:2]};
            3'b011: out = {3'b000, in[6:3]};
            3'b100: out = {4'b0000, in[6:4]};
            3'b101: out = {5'b00000, in[6:5]};
            3'b110: out = {6'b000000, in[6]};
            3'b111: out = 7'b0000000;  // Shift all bits out
        endcase
    end
endmodule

ALU_NOT_7bit.v
module ALU_NOT_7bit (
    input wire [6:0] A,
    output wire [6:0] result
);
    assign result = ~A;
endmodule

ALU_7bit.v
module ALU_7bit (
    input wire [6:0] A, B,
    input wire OP,          // 0: NOT, 1: SHR
    output reg [6:0] result,
    output wire ZF          // Zero flag
);
    wire [6:0] R_NOT, R_SHR;
    
    // Instantiate modules
    ALU_NOT_7bit NOT1 (.A(A), .result(R_NOT));
    ALU_SHR_7bit SHR1 (.in(A), .shift(B[2:0]), .out(R_SHR));
    
    always @(*) begin
        case (OP)
            1'b0: result = R_NOT;  // NOT operation
            1'b1: result = R_SHR;  // SHR operation
            default: result = 7'b0000000;
        endcase
    end
    
    // Zero flag (1 when result is all zeros)
    assign ZF = (result == 7'b0000000);
endmodule

controller.v
module controller (
    input wire clk, reset,
    output reg [6:0] A, B,
    output reg OP
);
    reg [2:0] pstate, nstate;
    
    parameter [2:0] START = 3'b000,
                    TEST_NOT = 3'b001,
                    TEST_SHR = 3'b010,
                    FINISH = 3'b011;
    
    // State register
    always @(posedge clk or posedge reset) begin
        if (reset)
            pstate <= START;
        else
            pstate <= nstate;
    end
    
    // Next state and output logic
    always @(*) begin
        // Default outputs
        A = 7'b0000000;
        B = 7'b0000000;
        OP = 1'b0;
        nstate = pstate;
        
        case (pstate)
            START: begin
                nstate = TEST_NOT;
            end
            
            TEST_NOT: begin
                A = 7'b1010101;  // Test pattern for NOT
                B = 7'b0000000;  // Not used for NOT operation
                OP = 1'b0;       // NOT operation
                nstate = TEST_SHR;
            end
            
            TEST_SHR: begin
                A = 7'b1100110;  // Test pattern for SHR
                B = 7'b0000011;  // Shift by 3
                OP = 1'b1;      // SHR operation
                nstate = FINISH;
            end
            
            FINISH: begin
                nstate = START;
            end
            
            default: nstate = START;
        endcase
    end
endmodule

top.v
module top (
    input wire clk, reset,
    output wire [6:0] result,
    output wire flag_gt_zero
);
    wire [6:0] A, B;
    wire OP;
    wire [6:0] R_result;
    wire R_ZF;
    
    controller controller_inst (
        .clk(clk),
        .reset(reset),
        .A(A),
        .B(B),
        .OP(OP)
    );
    
    ALU_7bit alu_inst (
        .A(A),
        .B(B),
        .OP(OP),
        .result(R_result),
        .ZF(R_ZF)
    );
    
    assign result = R_result;
    assign flag_gt_zero = ~R_ZF;  // Active high when result is not zero
endmodule

top_tb.v
`timescale 1ns/1ns
module top_tb;

    reg clk, reset;
    wire [6:0] result;
    wire flag_gt_zero;
    
    top uut (
        .clk(clk),
        .reset(reset),
        .result(result),
        .flag_gt_zero(flag_gt_zero)
    );
    
    initial begin
        clk = 0;
        forever #5 clk = ~clk;
    end
    
    initial begin
        $dumpfile("top_test.vcd");
        $dumpvars(0, top_tb);
        
        reset = 1;
        #10;
        reset = 0;
        
        #100;
        $finish;
    end
    
    initial begin
        $monitor("Time=%3t Result=%b Flag=%b", 
                $time, result, flag_gt_zero);
    end
endmodule

top_test.vcd
$date
	Sun Jun  8 22:58:40 2025
$end
$version
	Icarus Verilog
$end
$timescale
	1ns
$end
$scope module top_tb $end
$var wire 7 ! result [6:0] $end
$var wire 1 " flag_gt_zero $end
$var reg 1 # clk $end
$var reg 1 $ reset $end
$scope module uut $end
$var wire 1 # clk $end
$var wire 1 " flag_gt_zero $end
$var wire 1 $ reset $end
$var wire 7 % result [6:0] $end
$var wire 7 & R_result [6:0] $end
$var wire 1 ' R_ZF $end
$var wire 1 ( OP $end
$var wire 7 ) B [6:0] $end
$var wire 7 * A [6:0] $end
$scope module alu_inst $end
$var wire 1 ' ZF $end
$var wire 7 + R_SHR [6:0] $end
$var wire 7 , R_NOT [6:0] $end
$var wire 1 ( OP $end
$var wire 7 - B [6:0] $end
$var wire 7 . A [6:0] $end
$var reg 7 / result [6:0] $end
$scope module NOT1 $end
$var wire 7 0 result [6:0] $end
$var wire 7 1 A [6:0] $end
$upscope $end
$scope module SHR1 $end
$var wire 3 2 shift [2:0] $end
$var wire 7 3 in [6:0] $end
$var reg 7 4 out [6:0] $end
$upscope $end
$upscope $end
$scope module controller_inst $end
$var wire 1 # clk $end
$var wire 1 $ reset $end
$var parameter 3 5 FINISH $end
$var parameter 3 6 START $end
$var parameter 3 7 TEST_NOT $end
$var parameter 3 8 TEST_SHR $end
$var reg 7 9 A [6:0] $end
$var reg 7 : B [6:0] $end
$var reg 1 ( OP $end
$var reg 3 ; nstate [2:0] $end
$var reg 3 < pstate [2:0] $end
$upscope $end
$upscope $end
$upscope $end
$enddefinitions $end
$comment Show the parameter values. $end
$dumpall
b10 8
b1 7
b0 6
b11 5
$end
#0
$dumpvars
b0 <
b1 ;
b0 :
b0 9
b0 4
b0 3
b0 2
b0 1
b1111111 0
b1111111 /
b0 .
b0 -
b1111111 ,
b0 +
b0 *
b0 )
0(
0'
b1111111 &
b1111111 %
1$
0#
1"
b1111111 !
$end
#5
1#
#10
0#
0$
#15
b101010 !
b101010 %
b101010 &
b101010 /
b101010 ,
b101010 0
b1010101 +
b1010101 4
b10 ;
b1010101 *
b1010101 .
b1010101 1
b1010101 3
b1010101 9
b1 <
1#
#20
0#
#25
b1100 !
b1100 %
b1100 &
b1100 /
b11 2
b11001 ,
b11001 0
b1100 +
b1100 4
b11 ;
1(
b11 )
b11 -
b11 :
b1100110 *
b1100110 .
b1100110 1
b1100110 3
b1100110 9
b10 <
1#
#30
0#
#35
b1111111 !
b1111111 %
b1111111 &
b1111111 /
b0 2
b1111111 ,
b1111111 0
b0 +
b0 4
b0 ;
0(
b0 )
b0 -
b0 :
b0 *
b0 .
b0 1
b0 3
b0 9
b11 <
1#
#40
0#
#45
b1 ;
b0 <
1#
#50
0#
#55
b101010 !
b101010 %
b101010 &
b101010 /
b101010 ,
b101010 0
b1010101 +
b1010101 4
b10 ;
b1010101 *
b1010101 .
b1010101 1
b1010101 3
b1010101 9
b1 <
1#
#60
0#
#65
b1100 !
b1100 %
b1100 &
b1100 /
b11 2
b11001 ,
b11001 0
b1100 +
b1100 4
b11 ;
1(
b11 )
b11 -
b11 :
b1100110 *
b1100110 .
b1100110 1
b1100110 3
b1100110 9
b10 <
1#
#70
0#
#75
b1111111 !
b1111111 %
b1111111 &
b1111111 /
b0 2
b1111111 ,
b1111111 0
b0 +
b0 4
b0 ;
0(
b0 )
b0 -
b0 :
b0 *
b0 .
b0 1
b0 3
b0 9
b11 <
1#
#80
0#
#85
b1 ;
b0 <
1#
#90
0#
#95
b101010 !
b101010 %
b101010 &
b101010 /
b101010 ,
b101010 0
b1010101 +
b1010101 4
b10 ;
b1010101 *
b1010101 .
b1010101 1
b1010101 3
b1010101 9
b1 <
1#
#100
0#
#105
b1100 !
b1100 %
b1100 &
b1100 /
b11 2
b11001 ,
b11001 0
b1100 +
b1100 4
b11 ;
1(
b11 )
b11 -
b11 :
b1100110 *
b1100110 .
b1100110 1
b1100110 3
b1100110 9
b10 <
1#
